oneNeuron/__init__.py
oneNeuron/all_utils.py
oneNeuron/perceptron.py
oneNeuron_pypi_saquibquddus-0.0.7.dist-info/LICENSE
oneNeuron_pypi_saquibquddus-0.0.7.dist-info/METADATA
oneNeuron_pypi_saquibquddus-0.0.7.dist-info/WHEEL
oneNeuron_pypi_saquibquddus-0.0.7.dist-info/top_level.txt
oneNeuron_pypi_saquibquddus-0.0.7.dist-info/RECORD
