Metadata-Version: 2.1
Name: oneNeuron-pypi-saquibquddus
Version: 0.0.7
Summary: It's a implementation of Perceptron and all_utils
Home-page: https://github.com/saquibquddus/oneNeuron_pypi
Author: saquibquddus
Author-email: sakibquddus@gmail.com
License: UNKNOWN
Project-URL: Bug Tracker, https://github.com/saquibquddus/oneNeuron_pypi/issues
Platform: UNKNOWN
Classifier: Programming Language :: Python :: 3
Classifier: License :: OSI Approved :: MIT License
Classifier: Operating System :: OS Independent
Requires-Python: >=3.7
License-File: LICENSE
Requires-Dist: numpy
Requires-Dist: pandas
Requires-Dist: tqdm
Requires-Dist: matplotlib
Requires-Dist: joblib
